linkpredict/__init__.py
linkpredict/link.py
linkpredict/utils.py
linkpredict/antenna/__init__.py
linkpredict/antenna/antenna.py
linkpredict/antenna/base.py
linkpredict/antenna/noise.py
linkpredict/channel/__init__.py
linkpredict/channel/base.py
linkpredict/channel/modulation.py
linkpredict/path/__init__.py
linkpredict/path/base.py
linkpredict/path/geometry.py
linkpredict/path/loss.py
linkpredict/transceiver/__init__.py
linkpredict/transceiver/cable.py
linkpredict/transceiver/device.py
linkpredict/transceiver/receiver.py
linkpredict/transceiver/transmitter.py
linkpredict-2.2.1.dist-info/LICENSE.txt
linkpredict-2.2.1.dist-info/METADATA
linkpredict-2.2.1.dist-info/WHEEL
linkpredict-2.2.1.dist-info/top_level.txt
linkpredict-2.2.1.dist-info/RECORD
