Metadata-Version: 2.1
Name: linkpredict
Version: 2.2.1
Summary: A generic and dynamic link budget tool
Home-page: https://gitlab.com/librecube/lib/python-linkpredict
Author-email: info@librecube.org
License: MIT
Platform: UNKNOWN
Requires-Python: >=3.4
License-File: LICENSE.txt
Requires-Dist: numpy
Requires-Dist: scipy
Requires-Dist: skyfield
